{
  "type": "FeatureCollection",
  "features": [
    {
      "type": "Feature",
      "properties": {},
      "geometry": {
        "coordinates": [
          [
            126.00298156081101,
            8.168693463935554
          ],
          [
            126.00296661318242,
            8.168741166700812
          ],
          [
            126.00296266136758,
            8.168790063184943
          ],
          [
            126.0030011915565,
            8.16882233486345
          ],
          [
            126.00300514337135,
            8.168867319621043
          ],
          [
            126.0030189747261,
            8.168901547150483
          ],
          [
            126.00304070970617,
            8.168922083666686
          ],
          [
            126.00307627603684,
            8.168937730535134
          ]
        ],
        "type": "LineString"
      }
    },
    {
      "type": "Feature",
      "properties": {},
      "geometry": {
        "coordinates": [
          [
            126.00281324947196,
            8.168866104867533
          ],
          [
            126.00278037484799,
            8.16887528301892
          ],
          [
            126.0027701753948,
            8.168895474948656
          ],
          [
            126.00271546923352,
            8.168884461168801
          ],
          [
            126.00266725361843,
            8.168885378984982
          ],
          [
            126.00264727570095,
            8.168898062221999
          ],
          [
            126.00263244013212,
            8.16891917196692
          ],
          [
            126.00263522180154,
            8.168934774820812
          ]
        ],
        "type": "LineString"
      }
    },
    {
      "type": "Feature",
      "properties": {},
      "geometry": {
        "coordinates": [
          [
            126.0028392972693,
            8.168789960705254
          ],
          [
            126.00276132413791,
            8.168757636503514
          ],
          [
            126.00270383630715,
            8.168727348596803
          ],
          [
            126.0026216748534,
            8.168695194163334
          ]
        ],
        "type": "LineString"
      }
    },
    {
      "type": "Feature",
      "properties": {},
      "geometry": {
        "coordinates": [
          [
            126.00264733390281,
            8.168897851642257
          ],
          [
            126.00262570859292,
            8.16889519664899
          ],
          [
            126.00255291620692,
            8.168899722494444
          ],
          [
            126.00252264266965,
            8.168946544940127
          ],
          [
            126.00251885847473,
            8.169008818786182
          ],
          [
            126.00253464386071,
            8.169061769034471
          ],
          [
            126.00252234523646,
            8.169121701739499
          ],
          [
            126.00258052718999,
            8.169096417631067
          ],
          [
            126.00265479196156,
            8.169066451277772
          ],
          [
            126.00268033525816,
            8.169067387726486
          ],
          [
            126.00268270037913,
            8.169113741927589
          ]
        ],
        "type": "LineString"
      }
    },
    {
      "type": "Feature",
      "properties": {},
      "geometry": {
        "coordinates": [
          [
            126.00315933700574,
            8.169094299040381
          ],
          [
            126.00320494895647,
            8.169161154474438
          ],
          [
            126.00321109077225,
            8.169250152833698
          ],
          [
            126.00319267056057,
            8.16934652880812
          ],
          [
            126.00318916194857,
            8.169402096926945
          ]
        ],
        "type": "LineString"
      }
    },
    {
      "type": "Feature",
      "properties": {},
      "geometry": {
        "coordinates": [
          [
            126.00324069973851,
            8.168645261563583
          ],
          [
            126.00326234009907,
            8.168684354526107
          ],
          [
            126.00328450693183,
            8.168738210556967
          ],
          [
            126.00331593748376,
            8.168796105884255
          ],
          [
            126.00334406995466,
            8.168849122348874
          ],
          [
            126.00336514188092,
            8.168887089946082
          ],
          [
            126.00339667408895,
            8.168957651975404
          ],
          [
            126.00342677072166,
            8.169016241435898
          ],
          [
            126.0034588737966,
            8.169078803053367
          ],
          [
            126.00348796721704,
            8.169132427292467
          ],
          [
            126.00352307995564,
            8.169207898427317
          ]
        ],
        "type": "LineString"
      }
    },
    {
      "type": "Feature",
      "properties": {},
      "geometry": {
        "coordinates": [
          [
            126.00282653668444,
            8.169163988367018
          ],
          [
            126.00273810192436,
            8.169166120953534
          ]
        ],
        "type": "LineString"
      }
    },
    {
      "type": "Feature",
      "properties": {},
      "geometry": {
        "coordinates": [
          [
            126.00269450115547,
            8.169226770855147
          ],
          [
            126.0026742918555,
            8.169269765296917
          ],
          [
            126.0026382808723,
            8.169310361632299
          ],
          [
            126.0026202753798,
            8.16936382997443
          ],
          [
            126.00262321609051,
            8.169411429579341
          ]
        ],
        "type": "LineString"
      }
    },
    {
      "type": "Feature",
      "properties": {},
      "geometry": {
        "coordinates": [
          [
            126.00287214388857,
            8.169365183910244
          ],
          [
            126.00292953567538,
            8.169370752013592
          ],
          [
            126.00296253800161,
            8.169408511855508
          ],
          [
            126.00300992366329,
            8.169461670629886
          ],
          [
            126.00303045744977,
            8.169498412719506
          ]
        ],
        "type": "LineString"
      }
    },
    {
      "type": "Feature",
      "properties": {},
      "geometry": {
        "coordinates": [
          [
            126.00292924218621,
            8.169370553258432
          ],
          [
            126.00296281506053,
            8.169362552917264
          ],
          [
            126.00298768385585,
            8.169370553258432
          ],
          [
            126.0030327611367,
            8.169358569067526
          ],
          [
            126.00306230812419,
            8.169367852863886
          ]
        ],
        "type": "LineString"
      }
    },
    {
      "type": "Feature",
      "properties": {},
      "geometry": {
        "coordinates": [
          [
            126.0028333878031,
            8.16887488410731
          ],
          [
            126.00285315903915,
            8.168893951092201
          ],
          [
            126.00285775141936,
            8.168948717093585
          ],
          [
            126.00289462065439,
            8.168977201915212
          ],
          [
            126.00293674875502,
            8.168996111793149
          ],
          [
            126.00289707686102,
            8.169051450870413
          ],
          [
            126.00288722921613,
            8.16910472232287
          ],
          [
            126.00289859891626,
            8.169149523158396
          ],
          [
            126.00291168923286,
            8.169211211199908
          ],
          [
            126.00295501696809,
            8.169227094705917
          ],
          [
            126.00304362397782,
            8.169211412523396
          ],
          [
            126.0031154884216,
            8.169209868049805
          ],
          [
            126.00317729563312,
            8.169202686351696
          ],
          [
            126.00320848438929,
            8.1692035477366
          ]
        ],
        "type": "LineString"
      }
    },
    {
      "type": "Feature",
      "properties": {},
      "geometry": {
        "coordinates": [
          [
            126.00240633524834,
            8.16861898857843
          ],
          [
            126.00242132963365,
            8.16872348616144
          ],
          [
            126.00246490031924,
            8.168855039859295
          ],
          [
            126.00251502516409,
            8.168913304151118
          ],
          [
            126.00257631263275,
            8.168959822455946
          ]
        ],
        "type": "LineString"
      }
    }
  ]
}
